cfrx/__init__.py
cfrx/episode.py
cfrx/policy.py
cfrx/test.py
cfrx/utils.py
cfrx/algorithms/__init__.py
cfrx/algorithms/mccfr/__init__.py
cfrx/algorithms/mccfr/outcome_sampling copy.py
cfrx/algorithms/mccfr/outcome_sampling.py
cfrx/algorithms/mccfr/test_outcome_sampling.py
cfrx/envs/__init__.py
cfrx/envs/base.py
cfrx/envs/kuhn_poker/__init__.py
cfrx/envs/kuhn_poker/constants.py
cfrx/envs/kuhn_poker/env.py
cfrx/envs/kuhn_poker/data/__init__.py
cfrx/envs/kuhn_poker/data/info_states.npz
cfrx/envs/leduc_poker/__init__.py
cfrx/envs/leduc_poker/constants.py
cfrx/envs/leduc_poker/env.py
cfrx/envs/leduc_poker/data/__init__.py
cfrx/envs/leduc_poker/data/info_states.npz
cfrx/metrics/__init__.py
cfrx/metrics/best_response.py
cfrx/metrics/exploitability.py
cfrx/trainers/__init__.py
cfrx/trainers/mccfr.py
cfrx/tree/__init__.py
cfrx/tree/traverse.py
cfrx/tree/tree.py
cfrx-0.0.2.dist-info/LICENSE
cfrx-0.0.2.dist-info/METADATA
cfrx-0.0.2.dist-info/WHEEL
cfrx-0.0.2.dist-info/top_level.txt
cfrx-0.0.2.dist-info/RECORD
