Metadata-Version: 2.1
Name: cfrx
Version: 0.0.2
Summary: Counterfactual Regret Minimization in Jax
Author: Raphaël Boige
License: MIT License
Project-URL: repository, https://github.com/Egiob/cfrx
Keywords: jax,game-theory,reinforcement-learning,cfr,poker
Classifier: Development Status :: 3 - Alpha
Classifier: Intended Audience :: Developers
Classifier: Intended Audience :: Information Technology
Classifier: Intended Audience :: Science/Research
Classifier: License :: OSI Approved :: MIT License
Classifier: Natural Language :: English
Classifier: Programming Language :: Python :: 3
Classifier: Topic :: Scientific/Engineering :: Artificial Intelligence
Classifier: Topic :: Scientific/Engineering :: Information Analysis
Classifier: Topic :: Scientific/Engineering :: Mathematics
Requires-Python: >=3.9.0
License-File: LICENSE
Requires-Dist: jaxtyping >=0.2.19
Requires-Dist: jax >=0.4.0
Requires-Dist: flax >=0.7.0
Requires-Dist: pgx >=2.0.1
Requires-Dist: tqdm ~=4.66.0
